yacana/TokenCount.py
yacana/__init__.py
yacana/agent.py
yacana/base_tool_caller.py
yacana/constants.py
yacana/exceptions.py
yacana/function_to_json_schema.py
yacana/generic_agent.py
yacana/group_solve.py
yacana/history.py
yacana/langfuse_connector.py
yacana/logging_config.py
yacana/mcp.py
yacana/medias.py
yacana/messages.py
yacana/model_settings.py
yacana/ollama_agent.py
yacana/open_ai_agent.py
yacana/open_ai_tool_calling.py
yacana/structured_outputs.py
yacana/task.py
yacana/tool.py
yacana/utils.py
yacana/yacana_tool_calling.py
yacana-0.4.1.dist-info/licenses/LICENSE
yacana-0.4.1.dist-info/METADATA
yacana-0.4.1.dist-info/WHEEL
yacana-0.4.1.dist-info/top_level.txt
yacana-0.4.1.dist-info/RECORD
