Metadata-Version: 2.4
Name: yacana
Version: 0.4.1
Summary: Task-driven multi-agent framework giving you the building blocks to create anything you wish with LLMs.
Home-page: https://remembersoftwares.github.io/yacana/
Author: Emilien Lancelot
Author-email: remember.softwares@gmail.com
Project-URL: Github, https://github.com/rememberSoftwares/yacana
Classifier: Programming Language :: Python :: 3
Classifier: License :: OSI Approved :: MIT License
Classifier: Operating System :: OS Independent
Requires-Python: >=3.10
License-File: LICENSE
Requires-Dist: ollama>=0.4.6
Requires-Dist: pydantic>=2.7.3
Requires-Dist: pydantic_core>=2.18.4
Requires-Dist: openai>=1.61.1
Requires-Dist: requests>=2.32.4
Requires-Dist: regex>=2025.9.18
Requires-Dist: tiktoken>=0.12.0
Requires-Dist: transformers>=4.57.0
Requires-Dist: langfuse>=3.11.2
Dynamic: license-file
